ADScopeControl/CaptDeviceConfig.py
ADScopeControl/__init__.py
ADScopeControl/constants/dwfconstants.py
ADScopeControl/controller/AD2CaptDeviceSimulator.py
ADScopeControl/controller/BaseADScopeController.py
ADScopeControl/controller/__init__.py
ADScopeControl/controller/sweepHelpers.py
ADScopeControl/controller/DeviceInformation/AnalogOutChannel.py
ADScopeControl/controller/DeviceInformation/HWConnectedDeviceInformation.py
ADScopeControl/controller/DeviceInformation/HWDeviceBase.py
ADScopeControl/controller/DeviceInformation/HWDeviceInformation.py
ADScopeControl/controller/DeviceInformation/WaveFormsAPI.py
ADScopeControl/controller/DeviceInformation/dataclasses/AnalogInChannelInfo.py
ADScopeControl/controller/mp_AD2Capture/MPCaptDevice.py
ADScopeControl/controller/mp_AD2Capture/MPCaptDeviceControl.py
ADScopeControl/controller/mp_AD2Capture/__init__.py
ADScopeControl/model/AD2CaptDeviceSignals.py
ADScopeControl/model/AD2Constants.py
ADScopeControl/model/AD2ScopeModel.py
ADScopeControl/model/__init__.py
ADScopeControl/model/submodels/AD2CaptDeviceAnalogInModel.py
ADScopeControl/model/submodels/AD2CaptDeviceCapturingModel.py
ADScopeControl/model/submodels/AD2CaptDeviceInformationModel.py
ADScopeControl/model/submodels/AD2CaptDeviceSupervisorModel.py
ADScopeControl/model/submodels/__init__.py
ADScopeControl/resources/AD2ControlWindow.ui
ADScopeControl/resources/AD2ControlWindowNew.ui
ADScopeControl/resources/convert.sh
ADScopeControl/resources/resources.qrc
ADScopeControl/resources/icons/adscopecontrol_icon.png
ADScopeControl/resources/icons/cil-3d.png
ADScopeControl/resources/icons/cil-4k.png
ADScopeControl/resources/icons/cil-account-logout.png
ADScopeControl/resources/icons/cil-action-redo.png
ADScopeControl/resources/icons/cil-action-undo.png
ADScopeControl/resources/icons/cil-airplane-mode-off.png
ADScopeControl/resources/icons/cil-airplane-mode.png
ADScopeControl/resources/icons/cil-alarm.png
ADScopeControl/resources/icons/cil-align-center.png
pyadscopecontrol-1.2.7.dist-info/METADATA
pyadscopecontrol-1.2.7.dist-info/WHEEL
pyadscopecontrol-1.2.7.dist-info/licenses/LICENSE
pyadscopecontrol-1.2.7.dist-info/RECORD
