Metadata-Version: 2.3
Name: PyADScopeControl
Version: 1.2.7
Summary: A UI for controlling the Analog Discovery Series
Project-URL: Homepage, https://github.com/agentsmith29/PyADScopeControl
Author-email: Christoph Schmidt <cschmidt.fs@gmail.com>
Classifier: License :: OSI Approved :: GNU General Public License v3 (GPLv3)
Classifier: Operating System :: OS Independent
Classifier: Programming Language :: Python :: 3
Requires-Python: >=3.7
Requires-Dist: confpy6
Requires-Dist: matplotlib
Requires-Dist: mppy6
Requires-Dist: numpy
Requires-Dist: pandas
Requires-Dist: pyqtgraph
Requires-Dist: pyside6
Requires-Dist: pyside6widgetcollection>=1.0.2
Requires-Dist: rich
Requires-Dist: scipy
Requires-Dist: toml
